lambada/__init__.py
lambada/cli.py
lambada/models.py
lambada_ln_dev-1.0.0.dist-info/LICENSE
lambada_ln_dev-1.0.0.dist-info/METADATA
lambada_ln_dev-1.0.0.dist-info/WHEEL
lambada_ln_dev-1.0.0.dist-info/entry_points.txt
lambada_ln_dev-1.0.0.dist-info/top_level.txt
lambada_ln_dev-1.0.0.dist-info/RECORD
