Metadata-Version: 2.1
Name: lambada-ln-dev
Version: 1.0.0
Summary: A simple way to create AWS Lambda projects in Python heavily inspired and copied from https://github.com/nficano/python-lambda
Home-page: https://github.com/rustico/lambada
Author: ln-data-devs
Author-email: desarrollooldata@lanacion.com.ar
License: MIT license
Keywords: lambada
Platform: UNKNOWN
Classifier: Development Status :: 3 - Alpha
Classifier: Intended Audience :: Developers
Classifier: License :: OSI Approved :: MIT License
Classifier: Natural Language :: English
Classifier: Programming Language :: Python :: 3
Classifier: Programming Language :: Python :: 3.4
Classifier: Programming Language :: Python :: 3.5
Classifier: Programming Language :: Python :: 3.6
Classifier: Programming Language :: Python :: 3.7
Requires-Python: >=3.6
Requires-Dist: Click >=7
Requires-Dist: boto3 >=1.9
Requires-Dist: PyYAML >=5
